django_fsm_log/__init__.py
django_fsm_log/admin.py
django_fsm_log/apps.py
django_fsm_log/backends.py
django_fsm_log/conf.py
django_fsm_log/decorators.py
django_fsm_log/helpers.py
django_fsm_log/managers.py
django_fsm_log/models.py
django_fsm_log/migrations/0001_initial.py
django_fsm_log/migrations/0002_auto_20151207_1521.py
django_fsm_log/migrations/0003_statelog_description.py
django_fsm_log/migrations/0003_statelog_description_squashed_0005_description_null.py
django_fsm_log/migrations/0004_add_source_state.py
django_fsm_log/migrations/0004_auto_20190131_0341.py
django_fsm_log/migrations/0005_description_null.py
django_fsm_log/migrations/__init__.py
django_fsm_log-3.1.0.dist-info/LICENSE
django_fsm_log-3.1.0.dist-info/METADATA
django_fsm_log-3.1.0.dist-info/WHEEL
django_fsm_log-3.1.0.dist-info/top_level.txt
django_fsm_log-3.1.0.dist-info/RECORD
